quantum/__init__.py
quantum/quantum.py
quantumcomputingsim-1.0.4.dist-info/METADATA
quantumcomputingsim-1.0.4.dist-info/WHEEL
quantumcomputingsim-1.0.4.dist-info/top_level.txt
quantumcomputingsim-1.0.4.dist-info/RECORD
