Metadata-Version: 2.1
Name: quantumcomputingsim
Version: 1.0.4
Summary: A library to simulate quantum computations
Home-page: https://github.com/StealthyPanda/quantumcomputingsim
Author: Shaik Mohammed Touseef
Author-email: shaikm259@gmail.com
Project-URL: repository, https://github.com/StealthyPanda/quantumcomputingsim
Classifier: Programming Language :: Python :: 3
Classifier: License :: OSI Approved :: MIT License
Classifier: Operating System :: OS Independent
Requires-Python: >=3.6
